wrappity/__init__.py
wrappity/base.py
wrappity-0.1.4.dist-info/METADATA
wrappity-0.1.4.dist-info/WHEEL
wrappity-0.1.4.dist-info/entry_points.txt
wrappity-0.1.4.dist-info/licenses/LICENSE
wrappity-0.1.4.dist-info/RECORD
