Metadata-Version: 2.4
Name: wrappity
Version: 0.1.4
Summary: A package for easier access to deeply nested dictionaries.
Project-URL: Homepage, https://github.com/tomasrollo/wrappity
Project-URL: Issues, https://github.com/tomasrollo/wrappity/issues
Author-email: Tomas Rollo <tomas.rollo@gmail.com>
License-File: LICENSE
Classifier: License :: OSI Approved :: MIT License
Classifier: Operating System :: OS Independent
Classifier: Programming Language :: Python :: 3
Requires-Python: >=3.10
